[
    {
        "name": "Товары для кухни",
        "_id": "5e86f6611d19100f1c369ab1",
        "category": "5e86f6611d19100f1c369ab0"
    },
    {
        "name": "Товары для дома",
        "_id": "5e86f6611d19100f1c36b8a7",
        "category": "5e86f6611d19100f1c369ab0"
    },
    {
        "name": "Красота и здоровье",
        "_id": "5e86f6611d19100f1c36c682",
        "category": "5e86f6611d19100f1c369ab0"
    },
    {
        "name": "Смартфоны и гаджеты",
        "_id": "5e86f6611d19100f1c36cc31",
        "category": "5e86f6611d19100f1c36cc30"
    },
    {
        "name": "Фототехника",
        "_id": "5e86f6611d19100f1c36d4ab",
        "category": "5e86f6611d19100f1c36cc30"
    },
    {
        "name": "Планшеты, электронные книги",
        "_id": "5e86f6611d19100f1c36d9f6",
        "category": "5e86f6611d19100f1c36cc30"
    },
    {
        "name": "Телевизоры и аксессуары",
        "_id": "5e86f6611d19100f1c36db45",
        "category": "5e86f6611d19100f1c36db44"
    },
    {
        "name": "Игры и хобби",
        "_id": "5e86f6611d19100f1c36ddb7",
        "category": "5e86f6611d19100f1c36db44"
    },
    {
        "name": "Аудиотехника",
        "_id": "5e86f6611d19100f1c36e04f",
        "category": "5e86f6611d19100f1c36db44"
    },
    {
        "name": "Компьютеры, ноутбуки и ПО",
        "_id": "5e86f6611d19100f1c36e65d",
        "category": "5e86f6611d19100f1c36e65c"
    },
    {
        "name": "Комплектующие для ПК",
        "_id": "5e86f6611d19100f1c36ec5f",
        "category": "5e86f6611d19100f1c36e65c"
    },
    {
        "name": "Периферия и аксессуары",
        "_id": "5e86f6611d19100f1c36f7ab",
        "category": "5e86f6611d19100f1c36e65c"
    },
    {
        "name": "Оргтехника и офисное оборудование",
        "_id": "5e86f6611d19100f1c36fde3",
        "category": "5e86f6611d19100f1c36fde2"
    },
    {
        "name": "Маршрутизаторы и прочее беспроводное оборудование",
        "_id": "5e86f6611d19100f1c371263",
        "category": "5e86f6611d19100f1c36fde2"
    },
    {
        "name": "Профессиональное сетевое оборудование",
        "_id": "5e86f6611d19100f1c371384",
        "category": "5e86f6611d19100f1c36fde2"
    },
    {
        "name": "Для мобильных устройств",
        "_id": "5e86f6611d19100f1c3716ff",
        "category": "5e86f6611d19100f1c3716fe"
    },
    {
        "name": "Для компьютеров и ноутбуков",
        "_id": "5e86f6611d19100f1c371700",
        "category": "5e86f6611d19100f1c3716fe"
    },
    {
        "name": "Для бытовой техники",
        "_id": "5e86f6611d19100f1c371701",
        "category": "5e86f6611d19100f1c3716fe"
    },
    {
        "name": "Автоэлектроника и противоугонные системы",
        "_id": "5e86f6611d19100f1c371703",
        "category": "5e86f6611d19100f1c371702"
    },
    {
        "name": "Автозвук",
        "_id": "5e86f6611d19100f1c3717b3",
        "category": "5e86f6611d19100f1c371702"
    },
    {
        "name": "Наружные и внутрисалонные аксессуары",
        "_id": "5e86f6611d19100f1c3718fb",
        "category": "5e86f6611d19100f1c371702"
    },
    {
        "name": "Электроинструменты и техника для сада",
        "_id": "5e86f6611d19100f1c3719ee",
        "category": "5e86f6611d19100f1c3719ed"
    },
    {
        "name": "Строительство, измерение и уборка",
        "_id": "5e86f6611d19100f1c37258d",
        "category": "5e86f6611d19100f1c3719ed"
    },
    {
        "name": "Ручной инструмент и оснастка",
        "_id": "5e86f6611d19100f1c372aad",
        "category": "5e86f6611d19100f1c3719ed"
    }
]